LICENSE
MANIFEST.in
README.md
adjutant.py
setup.py
adjutant.egg-info/PKG-INFO
adjutant.egg-info/SOURCES.txt
adjutant.egg-info/dependency_links.txt
adjutant.egg-info/entry_points.txt
adjutant.egg-info/requires.txt
adjutant.egg-info/top_level.txt
test/test_sc2replay.py