Metadata-Version: 1.1
Name: adjutant
Version: 0.1.2
Summary: A Python library for parsing StarCraft II replays.
Home-page: http://github.com/arkx/adjutant/
Author: Aku Kotkavuo
Author-email: aku@hibana.net
License: UNKNOWN
Platform: UNKNOWN
Classifier: Development Status :: 3 - Alpha
Classifier: Environment :: Console
Classifier: Intended Audience :: End Users/Desktop
Classifier: Intended Audience :: Developers
Classifier: License :: OSI Approved :: BSD License
Classifier: Operating System :: MacOS :: MacOS X
Classifier: Operating System :: Microsoft :: Windows
Classifier: Operating System :: POSIX
Classifier: Programming Language :: Python :: 2.7
Classifier: Topic :: Games/Entertainment :: Real Time Strategy
Classifier: Topic :: Software Development :: Libraries
Requires: mpyq
